EasyPY/__init__.py
EasyPY/core.py
easypythonno-0.0.2.dist-info/METADATA
easypythonno-0.0.2.dist-info/WHEEL
easypythonno-0.0.2.dist-info/top_level.txt
easypythonno-0.0.2.dist-info/RECORD
