Metadata-Version: 2.4
Name: EasyPythonNO
Version: 0.0.2
Summary: Easy Version Of Python!
Author-email: SH_Dev <sh-dev@luna-tools.store>
License: MIT
Requires-Python: >=3.7
